sqladmin/__init__.py
sqladmin/_menu.py
sqladmin/_queries.py
sqladmin/_types.py
sqladmin/_validators.py
sqladmin/ajax.py
sqladmin/application.py
sqladmin/authentication.py
sqladmin/exceptions.py
sqladmin/fields.py
sqladmin/formatters.py
sqladmin/forms.py
sqladmin/helpers.py
sqladmin/models.py
sqladmin/pagination.py
sqladmin/py.typed
sqladmin/templating.py
sqladmin/utils.py
sqladmin/widgets.py
sqladmin/statics/css/flatpickr.min.css
sqladmin/statics/css/fontawesome.min.css
sqladmin/statics/css/main.css
sqladmin/statics/css/select2.min.css
sqladmin/statics/css/tabler.min.css
sqladmin/statics/js/bootstrap.min.js
sqladmin/statics/js/flatpickr.min.js
sqladmin/statics/js/jquery.min.js
sqladmin/statics/js/main.js
sqladmin/statics/js/popper.min.js
sqladmin/statics/js/select2.full.min.js
sqladmin/statics/js/tabler.min.js
sqladmin/statics/webfonts/fa-brands-400.woff2
sqladmin/statics/webfonts/fa-regular-400.woff2
sqladmin/statics/webfonts/fa-solid-900.woff2
sqladmin/templates/_macros.html
sqladmin/templates/base.html
sqladmin/templates/create.html
sqladmin/templates/details.html
sqladmin/templates/edit.html
sqladmin/templates/error.html
sqladmin/templates/index.html
sqladmin/templates/layout.html
sqladmin/templates/list.html
sqladmin/templates/login.html
sqladmin/templates/modals/delete.html
sqladmin/templates/modals/details_action_confirmation.html
sqladmin/templates/modals/list_action_confirmation.html
sqladmin_litestar-0.16.1.dist-info/METADATA
sqladmin_litestar-0.16.1.dist-info/WHEEL
sqladmin_litestar-0.16.1.dist-info/licenses/LICENSE.md
sqladmin_litestar-0.16.1.dist-info/RECORD
